proxymana/__init__.py
proxymana/proxymana.py
proxymana-1.0.1.dist-info/LICENSE
proxymana-1.0.1.dist-info/METADATA
proxymana-1.0.1.dist-info/WHEEL
proxymana-1.0.1.dist-info/RECORD
