Metadata-Version: 2.1
Name: proxymana
Version: 1.0.1
Summary: Simple proxy management tool for scraping and managing free anonymous proxies
Home-page: https://github.com/SlowWave/ProxyMana
License: MIT
Author: SlowWave
Author-email: chrs.borgia@gmail.com
Requires-Python: >=3.12,<4.0
Classifier: License :: OSI Approved :: MIT License
Classifier: Programming Language :: Python :: 3
Classifier: Programming Language :: Python :: 3.12
Requires-Dist: lxml (>=5.2.2,<6.0.0)
Requires-Dist: requests (>=2.32.3,<3.0.0)
Requires-Dist: schedule (>=1.2.2,<2.0.0)
Project-URL: Repository, https://github.com/SlowWave/ProxyMana
